{
  "157": "BFF Restaurante",
  "138": "BFF Restaurante Client",
  "1": "BFF Restaurante Mesas Mesa Service",
  "36": "BFF Restaurante Mesa Mesas Service",
  "6": "BFF Restaurante Mesas Mesa Service",
  "33": "BFF Restaurante Pedido Mesa Service",
  "105": "BFF Restaurante Mesa Mesas Service",
  "13": "BFF Restaurante Pedido Garcom Service",
  "46": "BFF Restaurante Mesas Pedidos Service",
  "20": "BFF Restaurante Garcom Mesa Controller",
  "47": "BFF Restaurante Notificacoes Garcom Service",
  "78": "BFF Restaurante Pedidos Pedido Client",
  "39": "BFF Restaurante Pedido Pedidos Service",
  "60": "BFF Restaurante Cozinha Pedidos Service",
  "19": "BFF Restaurante Pedido Pedidos Enums",
  "84": "BFF Restaurante Pedido Pedidos Mapper",
  "29": "BFF Restaurante Pedido Pedidos Mapper",
  "0": "BFF Restaurante Produtos Produto Service",
  "34": "BFF Restaurante Cardapio Produtos Mapper",
  "2": "BFF Restaurante Usuarios Login Service",
  "3": "BFF Restaurante Usuario Usuarios Service",
  "61": "BFF Restaurante Garcom Usuarios Mapper",
  "152": "BFF Restaurante Usuarios Client DTO",
  "153": "BFF Restaurante Usuarios Client",
  "134": "BFF Restaurante Config",
  "139": "BFF Restaurante Config",
  "72": "BFF Restaurante Auth Config Service",
  "131": "BFF Restaurante Auth Config Exception",
  "90": "BFF Restaurante Cardapio Mesa Controller",
  "73": "BFF Restaurante Cozinha Fila Controller",
  "43": "BFF Restaurante Garcom Auth Controller",
  "96": "BFF Restaurante Mesa Garcom Controller",
  "97": "BFF Restaurante Pedido Garcom Controller",
  "40": "BFF Restaurante Mesa Gestor Controller",
  "98": "BFF Restaurante Mesa Auth Controller",
  "15": "BFF Restaurante Garcom Mesa Service",
  "16": "BFF Restaurante Pedido Mesa Controller",
  "79": "BFF Restaurante Controller Response",
  "53": "BFF Restaurante Pedido Auth Controller",
  "48": "BFF Restaurante Pedido Cozinha Service",
  "74": "BFF Restaurante Pedido Garcom Request",
  "154": "BFF Restaurante DTO",
  "54": "BFF Restaurante Mesa Gestor Controller",
  "155": "BFF Restaurante Request DTO",
  "85": "BFF Restaurante Cardapio Categoria Controller",
  "22": "BFF Restaurante Mesa Garcom Response",
  "99": "BFF Restaurante Cozinha Fila Response",
  "80": "BFF Restaurante Mesa Auth Service",
  "115": "BFF Restaurante Cozinha Pedido Controller",
  "156": "BFF Restaurante Response DTO",
  "30": "BFF Restaurante Exception Response",
  "25": "BFF Restaurante Mesa Garcom Exception",
  "106": "BFF Restaurante Gestor Mesa Mapper",
  "112": "BFF Restaurante Auth Response Component",
  "110": "Usuarios MS Auth Request Response",
  "21": "BFF Restaurante Garcom Usuarios Tests",
  "104": "BFF Restaurante Auth Usuario Security",
  "107": "BFF Restaurante Usuario Service Security",
  "41": "BFF Restaurante Garcom Auth Service",
  "158": "DB Migrations",
  "145": "DB Migrations",
  "140": "DB Migrations Tests",
  "159": "Cozinha MS",
  "146": "Cozinha MS",
  "141": "Cozinha Tests MS",
  "160": "Mesas Mesa MS",
  "123": "Mesas Mesa Tests MS",
  "119": "Pedido Pedidos Client Response MS",
  "31": "Mesa Mesas Service Request MS",
  "32": "Mesa Mesas Controller Response MS",
  "17": "Mesa Garcom Mapper Response MS",
  "65": "Historico Mesas Repository Response MS",
  "52": "Mesa Mesas Service Response MS",
  "4": "Pedidos MS Pedido Produto Exception",
  "108": "Mesas Mesa Service MS",
  "75": "Pedidos MS Mesa Mesas Repository",
  "161": "Notificacoes MS",
  "147": "Notificacoes MS",
  "86": "Operacao Garcom Controller Request MS",
  "100": "Pedido Garcom Enums Request MS",
  "7": "Garcom Operacao Mapper Service MS",
  "81": "Exception Response MS Notificacoes",
  "142": "Notificacoes Tests MS",
  "49": "Garcom Notificacoes Service Response MS",
  "162": "Pedidos MS Pedido",
  "124": "Pedidos MS Pedido Tests",
  "27": "Pedidos MS Pedido Controller Response",
  "11": "Pedidos MS Pedido Mapper Enums",
  "71": "Pedidos MS Pedido Request Service",
  "8": "Pedidos MS Pedido Service Repository",
  "91": "Pedidos MS Pedido Cozinha Enums",
  "135": "Pedidos MS Pedido Response Service",
  "66": "Pedidos MS Pedido Produto Exception",
  "67": "Pedidos MS Exception Response Exceptions",
  "101": "Pedidos MS Pedido Service",
  "120": "Pedidos MS Pedido Mesa Request",
  "163": "Produtos MS Produto",
  "127": "Produtos MS Produto Tests",
  "125": "Produtos MS Cardapio Mesa Controller",
  "9": "Produtos MS Categoria Categorias Service",
  "55": "Produtos MS Produto Controller Response",
  "126": "Produtos MS Produto Request Validation",
  "50": "Produtos MS Produto Mapper Request",
  "62": "Produtos MS Produto Service Request",
  "63": "Produtos MS Cardapio Categoria Service",
  "37": "Produtos MS Cardapio Produto Mapper",
  "82": "Produtos MS Categoria Produto Exception",
  "64": "Produtos MS Exception Response",
  "10": "Produtos MS Validation Mapper Support",
  "28": "Produtos MS Produto Mapper Response",
  "109": "Produtos MS Produto Service",
  "164": "Usuarios MS Usuario",
  "128": "Usuarios MS Usuario Tests",
  "143": "Usuarios MS Config",
  "116": "Usuarios MS Config",
  "68": "Usuarios MS Usuario Controller Response",
  "56": "Usuarios MS Usuario Service Request",
  "87": "Usuarios MS Usuario Service Request",
  "92": "Usuarios MS Usuario Mapper Response",
  "117": "Usuarios MS Usuario Garcom Enums",
  "76": "Usuarios MS Usuario Exception",
  "57": "Usuarios MS Exception Response",
  "58": "Usuarios MS Usuario Auth Repository",
  "121": "Usuarios MS Service Security",
  "118": "Usuarios MS Usuario Service Validation",
  "93": "Usuarios MS Usuario Mesa Service",
  "102": "Auth Components Config Shared",
  "77": "Auth Routing Utils Core",
  "42": "Gestor Mesa Components Models Core",
  "18": "Gestor Garcom Components Component Shared",
  "23": "Garcom Expediente Service Core",
  "35": "Login Auth Models Components Features",
  "38": "Mesa Components Service Core",
  "94": "Service Models Core",
  "5": "Cozinha Pedido Models Response Features",
  "44": "Garcom Mesa Models Response Features",
  "88": "Cardapio Pedido Models Components Features",
  "122": "Cardapio Produto Components Models Features",
  "111": "Mesa Pedido Models Service Core",
  "103": "Mesa Garcom Models Request Core",
  "51": "Garcom Mesa Models Service Core",
  "45": "Pedido Pedidos Components Models Features",
  "83": "Mesa Pedido Models Response Features",
  "14": "Expediente Pedido Models Response Core",
  "69": "Produto Produtos Models Components Core",
  "148": "Core",
  "89": "Auth Login Service Core",
  "136": "Mesa Service Core",
  "59": "Components Service Features",
  "113": "Mesas Mesa Core",
  "24": "Gestor Garcom Component Config Features",
  "12": "Produtos Produto Utils Component Features",
  "70": "Component Features",
  "132": "Components Component Features",
  "129": "Components Component Features",
  "26": "Component Features",
  "133": "Gestor Mesas Features",
  "149": "Component Features",
  "137": "Login Components Component Features",
  "95": "Mesa Pedido Component Features",
  "130": "Component Features",
  "144": "Components Component Features",
  "114": "Mesa Component Features",
  "150": "Component Features",
  "151": "Components Component Shared"
}